{
  "name": "Infusing",
  "description": "Infusing at the altar is a powerful tool, yet its possibilities are still limited. Circle magic offers much more - this section presents rituals that allow the transformation of ordinary items into powerful artifacts, repairing them, infusing familiar objects with power, and enchanting inert materials.",
  "icon": "ars_maleficarum:textures/books/shadow_grimoire/icon/rituals/infusing.png",
  "parent": "ars_maleficarum:circle_magic/rituals",
  "sortnum": 1
}
