{
  "type": "minecraft:block",
  "functions": [
    {
      "function": "minecraft:explosion_decay"
    }
  ],
  "pools": [
    {
      "bonus_rolls": 0.0,
      "conditions": [
        {
          "block": "ars_maleficarum:swamp_rotfiend",
          "condition": "minecraft:block_state_property",
          "properties": {
            "age": "3"
          }
        }
      ],
      "entries": [
        {
          "type": "minecraft:item",
          "name": "ars_maleficarum:swamp_rotfiend_ingredient_item"
        }
      ],
      "rolls": 1.0
    }
  ],
  "random_sequence": "ars_maleficarum:blocks/swamp_rotfiend"
}